treemodel2sql/__init__.py
treemodel2sql/lgb2sql.py
treemodel2sql/xgboost2sql.py
treemodel2sql-0.1.5.dist-info/AUTHORS.rst
treemodel2sql-0.1.5.dist-info/LICENSE
treemodel2sql-0.1.5.dist-info/METADATA
treemodel2sql-0.1.5.dist-info/WHEEL
treemodel2sql-0.1.5.dist-info/entry_points.txt
treemodel2sql-0.1.5.dist-info/top_level.txt
treemodel2sql-0.1.5.dist-info/RECORD
