Metadata-Version: 2.1
Name: treemodel2sql
Version: 0.1.5
Summary: tree model transform to sql
Home-page: https://github.com/ZhengRyan/treemodel2sql
Author: RyanZheng
Author-email: zhengruiping000@163.com
License: MIT license
Keywords: treemodel2sql
Classifier: Development Status :: 2 - Pre-Alpha
Classifier: Intended Audience :: Developers
Classifier: License :: OSI Approved :: MIT License
Classifier: Natural Language :: English
Classifier: Programming Language :: Python :: 3
Classifier: Programming Language :: Python :: 3.6
Classifier: Programming Language :: Python :: 3.7
Classifier: Programming Language :: Python :: 3.8
Requires-Python: >=3.6
License-File: LICENSE
License-File: AUTHORS.rst
Requires-Dist: xgboost
Requires-Dist: lightgbm
Requires-Dist: pyspark
